kaniko/__init__.py
kaniko/kaniko.py
pykaniko-1.1.0.dist-info/LICENSE
pykaniko-1.1.0.dist-info/METADATA
pykaniko-1.1.0.dist-info/WHEEL
pykaniko-1.1.0.dist-info/top_level.txt
pykaniko-1.1.0.dist-info/zip-safe
pykaniko-1.1.0.dist-info/RECORD
