Metadata-Version: 2.1
Name: pykaniko
Version: 1.1.0
Summary: Python kaniko https://github.com/GoogleContainerTools/kaniko
Home-page: https://github.com/nxexox/pykaniko
Author: Deys Timofey
Author-email: nxexox@gmail.com
Maintainer: Deys Timofey
Maintainer-email: nxexox@gmail.com
License: Apache 2.0
Classifier: Environment :: Other Environment
Classifier: Intended Audience :: Developers
Classifier: License :: OSI Approved :: Apache Software License
Classifier: Operating System :: OS Independent
Classifier: Programming Language :: Python
Classifier: Programming Language :: Python :: 3.6
Classifier: Programming Language :: Python :: 3.7
Classifier: Programming Language :: Python :: 3.8
Classifier: Programming Language :: Python :: 3.9
Classifier: Programming Language :: Python :: 3.10
License-File: LICENSE
